flickr_url_parser/__init__.py
flickr_url_parser/base58.py
flickr_url_parser/cli.py
flickr_url_parser/exceptions.py
flickr_url_parser/matcher.py
flickr_url_parser/parser.py
flickr_url_parser/py.typed
flickr_url_parser/types.py
flickr_url_parser-1.12.0.dist-info/licenses/LICENSE-APACHE
flickr_url_parser-1.12.0.dist-info/licenses/LICENSE-MIT
flickr_url_parser-1.12.0.dist-info/METADATA
flickr_url_parser-1.12.0.dist-info/WHEEL
flickr_url_parser-1.12.0.dist-info/entry_points.txt
flickr_url_parser-1.12.0.dist-info/top_level.txt
flickr_url_parser-1.12.0.dist-info/RECORD
