Metadata-Version: 2.4
Name: flickr-url-parser
Version: 1.12.0
Summary: Enter a Flickr URL, and find out what sort of URL it is (single photo, album, gallery, etc.)
Author-email: Flickr Foundation <hello@flickr.org>
Maintainer-email: Alex Chan <alex@flickr.org>
Project-URL: Homepage, https://github.com/Flickr-Foundation/flickr-url-parser
Project-URL: Changelog, https://github.com/Flickr-Foundation/flickr-url-parser/blob/main/CHANGELOG.md
Keywords: flickr
Classifier: Development Status :: 5 - Production/Stable
Classifier: License :: OSI Approved :: Apache Software License
Classifier: License :: OSI Approved :: MIT License
Classifier: Programming Language :: Python :: 3.12
Requires-Python: >=3.12
License-File: LICENSE-APACHE
License-File: LICENSE-MIT
Requires-Dist: httpx
Requires-Dist: hyperlink
Dynamic: license-file
